{"chrome://browser/content/browser.xhtml":{"main-window":{"screenX":"0","screenY":"36","width":"1440","height":"814","sizemode":"normal"},"sidebar-box":{"sidebarcommand":"viewBookmarksSidebar","width":"","style":"--sidebar-background-color: rgb(56, 56, 61); --sidebar-text-color: rgb(249, 249, 250);"},"sidebar-title":{"value":"ブックマーク"},"place:535X+ukSIOMV/Wdb9Ns7aw==":{"open":"true"}},"chrome://browser/content/places/bookmarkProperties.xul":{"bookmarkproperties":{"screenX":"555","screenY":"0","width":"330"}},"chrome://browser/content/places/places.xul":{"placesContentTags":{"ordinal":"3"},"placesContentUrl":{"ordinal":"5"},"placesContentDate":{"ordinal":"7","sortDirection":"descending"},"placesContentVisitCount":{"ordinal":"9"},"placesContentDateAdded":{"ordinal":"11"},"placesContentLastModified":{"ordinal":"13"}},"chrome://browser/content/places/places.xhtml":{"placesContentTags":{"ordinal":"3"},"placesContentUrl":{"ordinal":"5"},"placesContentDate":{"ordinal":"7","sortDirection":"descending"},"placesContentVisitCount":{"ordinal":"9"},"placesContentDateAdded":{"ordinal":"11"},"placesContentLastModified":{"ordinal":"13"}}}